authcard/__init__.py
authcard/encryptutils/__init__.py
authcard/encryptutils/bcrypt.py
authcard/encryptutils/ctr.py
tests/__init__.py
tests/test_sample.py
tdctlauthcard-0.0.14.dist-info/LICENSE
tdctlauthcard-0.0.14.dist-info/METADATA
tdctlauthcard-0.0.14.dist-info/WHEEL
tdctlauthcard-0.0.14.dist-info/top_level.txt
tdctlauthcard-0.0.14.dist-info/RECORD
