Metadata-Version: 2.1
Name: tdctlauthcard
Version: 0.0.14
Summary: Auth utility
Home-page: https://github.com/teradactol/authcard.py
Author: Bishaka Samuel
Author-email: sbishaka@gmail.com
License: UNKNOWN
Platform: UNKNOWN
Classifier: Programming Language :: Python :: 3
Classifier: License :: OSI Approved :: MIT License
Classifier: Operating System :: OS Independent
Requires-Dist: python-jose[cryptography]
Requires-Dist: bcrypt
